odoo/addons/payment_cielo/README.rst
odoo/addons/payment_cielo/__init__.py
odoo/addons/payment_cielo/__manifest__.py
odoo/addons/payment_cielo/controllers/__init__.py
odoo/addons/payment_cielo/controllers/main.py
odoo/addons/payment_cielo/data/payment_acquirer_data.xml
odoo/addons/payment_cielo/i18n/payment_cielo.pot
odoo/addons/payment_cielo/i18n/pt_BR.po
odoo/addons/payment_cielo/models/__init__.py
odoo/addons/payment_cielo/models/payment_acquirer.py
odoo/addons/payment_cielo/models/payment_token.py
odoo/addons/payment_cielo/models/payment_transaction.py
odoo/addons/payment_cielo/readme/CONFIGURE.rst
odoo/addons/payment_cielo/readme/CONTRIBUTORS.rst
odoo/addons/payment_cielo/readme/CREDITS.rst
odoo/addons/payment_cielo/readme/DESCRIPTION.rst
odoo/addons/payment_cielo/readme/HISTORY.rst
odoo/addons/payment_cielo/readme/INSTALL.rst
odoo/addons/payment_cielo/readme/ROADMAP.rst
odoo/addons/payment_cielo/readme/USAGE.rst
odoo/addons/payment_cielo/static/description/icon.png
odoo/addons/payment_cielo/static/description/index.html
odoo/addons/payment_cielo/static/src/img/cielo_icon.png
odoo/addons/payment_cielo/static/src/xml/cielo_templates.xml
odoo/addons/payment_cielo/tests/__init__.py
odoo/addons/payment_cielo/tests/test_cielo.py
odoo/addons/payment_cielo/tests/fixtures/test_10_cielo_s2s.yaml
odoo/addons/payment_cielo/views/payment_cielo_templates.xml
odoo/addons/payment_cielo/views/payment_views.xml
odoo12_addon_payment_cielo-12.0.3.2.1.dist-info/METADATA
odoo12_addon_payment_cielo-12.0.3.2.1.dist-info/WHEEL
odoo12_addon_payment_cielo-12.0.3.2.1.dist-info/top_level.txt
odoo12_addon_payment_cielo-12.0.3.2.1.dist-info/RECORD
