Metadata-Version: 2.1
Name: odoo12-addon-payment-cielo
Version: 12.0.3.2.1
Summary: Payment Acquirer: Cielo Implementation
Home-page: https://github.com/OCA/l10n-brazil
Author: KMEE INFORMATICA LTDA,Odoo Community Association (OCA)
Author-email: support@odoo-community.org
License: AGPL-3
Platform: UNKNOWN
Classifier: Programming Language :: Python
Classifier: Framework :: Odoo
Classifier: License :: OSI Approved :: GNU Affero General Public License v3
Classifier: Development Status :: 3 - Alpha
Requires-Python: >=3.5
Requires-Dist: odoo (<12.1dev,>=12.0a)
